ode/__init__.py
ode/_functions.py
ode/integrators.py
ode-0.4.0.dist-info/LICENSE
ode-0.4.0.dist-info/METADATA
ode-0.4.0.dist-info/WHEEL
ode-0.4.0.dist-info/top_level.txt
ode-0.4.0.dist-info/RECORD
