Metadata-Version: 1.1
Name: ode
Version: 0.4.0
Summary: Ordinary differential equation solver (numeric integration)
Home-page: https://github.com/bierschenk/ode
Author: bierschenk
Author-email: bierschenk.devel@gmail.com
License: MIT license
Keywords: ode
Platform: UNKNOWN
Classifier: Development Status :: 3 - Alpha
Classifier: License :: OSI Approved :: MIT License
Classifier: Natural Language :: English
Classifier: Programming Language :: Python :: 3
Classifier: Programming Language :: Python :: 3.6
Classifier: Topic :: Scientific/Engineering
